adbc/__init__.py
adbc/add_jsondiff_representer.py
adbc/cli.py
adbc/commands/__init__.py
adbc/commands/diff.py
adbc/commands/run.py
adbc/config.py
adbc/database.py
adbc/host.py
adbc/namespace.py
adbc/query.py
adbc/store.py
adbc/table.py
adbc/template.py
adbc/utils.py
adbc/workflow.py
adbc-0.0.1.dist-info/entry_points.txt
adbc-0.0.1.dist-info/LICENSE.md
adbc-0.0.1.dist-info/WHEEL
adbc-0.0.1.dist-info/METADATA
adbc-0.0.1.dist-info/RECORD
