Metadata-Version: 2.1
Name: adbc
Version: 0.0.1
Summary: 
Author: aleontiev
Author-email: alonetiev@gmail.com
Requires-Python: >=3.7,<4.0
Classifier: Programming Language :: Python :: 3
Classifier: Programming Language :: Python :: 3.7
Classifier: Programming Language :: Python :: 3.8
Requires-Dist: asyncpg (>=0.18.3,<0.19.0)
Requires-Dist: cached_property (>=1.5.1,<2.0.0)
Requires-Dist: cleo (>=0.7.5,<0.8.0)
Requires-Dist: ipython (>=7.6.1,<8.0.0)
Requires-Dist: jsondiff (>=1.2.0,<2.0.0)
Requires-Dist: pyaml (>=19.12.0,<20.0.0)
Requires-Dist: pyyaml (>=5.3,<6.0)
Requires-Dist: uvloop (>=0.12.2,<0.13.0)
